MANIFEST.in
setup.cfg
setup.py
versioneer.py
drive_casa.egg-info/PKG-INFO
drive_casa.egg-info/SOURCES.txt
drive_casa.egg-info/dependency_links.txt
drive_casa.egg-info/requires.txt
drive_casa.egg-info/top_level.txt
drivecasa/__init__.py
drivecasa/_version.py
drivecasa/casa_env.py
drivecasa/interface.py
drivecasa/utils.py
drivecasa/commands/__init__.py
drivecasa/commands/format.py
drivecasa/commands/reduction.py
drivecasa/commands/simulation.py
drivecasa/commands/subroutines.py
tests/__init__.py
tests/test_command_logging.py
tests/test_installation.py
tests/test_interface.py
tests/sample_data/__init__.py
tests/test_commands/__init__.py
tests/test_commands/test_clean.py
tests/test_commands/test_concat.py
tests/test_commands/test_exportfits.py
tests/test_commands/test_import_uvfits.py
tests/test_commands/test_simcommands.py