Metadata-Version: 1.0
Name: drive-casa
Version: 0.7.6
Summary: An interfacing package for scripting CASA from an external pipeline.
Home-page: https://github.com/timstaley/drive-casa
Author: Tim Staley
Author-email: github@timstaley.co.uk
License: BSD 3-clause
Platform: UNKNOWN
